ukboards/__init__.py
ukboards/charities.py
ukboards/cli.py
ukboards/companies.py
ukboards/company_codes.py
ukboards/py.typed
ukboards/ukboards.py
ukboards/utils.py
ukboards-0.5.4.dist-info/AUTHORS.rst
ukboards-0.5.4.dist-info/LICENSE
ukboards-0.5.4.dist-info/METADATA
ukboards-0.5.4.dist-info/WHEEL
ukboards-0.5.4.dist-info/entry_points.txt
ukboards-0.5.4.dist-info/top_level.txt
ukboards-0.5.4.dist-info/RECORD
