Metadata-Version: 2.1
Name: ukboards
Version: 0.5.4
Summary: Query UK company and charity board networks.
Home-page: https://github.com/griff-rees/ukboards
Author: Griffith Rees
Author-email: griff.rees@gmail.com
License: MIT
Keywords: ukboards
Platform: UNKNOWN
Classifier: Development Status :: 2 - Pre-Alpha
Classifier: Intended Audience :: Developers
Classifier: License :: OSI Approved :: MIT License
Classifier: Natural Language :: English
Classifier: Programming Language :: Python :: 3 :: Only
Classifier: Programming Language :: Python :: 3.8
Classifier: Programming Language :: Python :: 3.9
Classifier: Topic :: Scientific/Engineering :: Information Analysis
Requires-Python: !=3.0.*, !=3.1.*, !=3.2.*, !=3.3.*, !=3.4.*, !=3.5.*, !=3.6.*, !=3.7.*
License-File: LICENSE
License-File: AUTHORS.rst
Requires-Dist: Click (>=7.1)
Requires-Dist: networkx (>=2.4)
Requires-Dist: requests (>=2.22.0)
Requires-Dist: zeep (>=4.0.0)
Requires-Dist: python-dotenv (>=0.15.0)
